coscli/__init__.py
coscli/__main__.py
coscli/command.py
coscli/cos.py
coscli/main.py
coscli/tools.py
coscli/utils.py
coscli-0.14.dist-info/DESCRIPTION.rst
coscli-0.14.dist-info/METADATA
coscli-0.14.dist-info/RECORD
coscli-0.14.dist-info/WHEEL
coscli-0.14.dist-info/entry_points.txt
coscli-0.14.dist-info/metadata.json
coscli-0.14.dist-info/top_level.txt
