Metadata-Version: 2.0
Name: coscli
Version: 0.14
Summary: Coscli is simple command line tool for qcloud COS.
Home-page: https://github.com/SerhoLiu/coscli
Author: Serho Liu
Author-email: serholiu@gmail.com
License: MIT License
Platform: UNKNOWN
Classifier: Development Status :: 3 - Alpha
Classifier: Environment :: Console
Classifier: Intended Audience :: Developers
Classifier: License :: OSI Approved :: MIT License
Classifier: Natural Language :: Chinese (Simplified)
Classifier: Operating System :: MacOS
Classifier: Operating System :: POSIX
Classifier: Programming Language :: Python :: 2.6
Classifier: Programming Language :: Python :: 2.7
Classifier: Programming Language :: Python :: 2 :: Only
Requires-Dist: click (>=4.0)
Requires-Dist: qcloud-cos-v4 (>=0.0.12)
